setup.py
src/RLxHC.egg-info/PKG-INFO
src/RLxHC.egg-info/SOURCES.txt
src/RLxHC.egg-info/dependency_links.txt
src/RLxHC.egg-info/top_level.txt
src/VMKUTB/__init__.py